secprompt/__init__.py
secprompt/check_prompt.py
secprompt-0.0.2.dist-info/METADATA
secprompt-0.0.2.dist-info/WHEEL
secprompt-0.0.2.dist-info/top_level.txt
secprompt-0.0.2.dist-info/RECORD
