Metadata-Version: 2.1
Name: secprompt
Version: 0.0.2
Summary: Protecting LLM-integrated applications from prompt injection attacks
Author-email: MagicBoy <3328254556@qq.com>
Classifier: Programming Language :: Python :: 3
Classifier: License :: OSI Approved :: Apache Software License
Classifier: Operating System :: OS Independent
Requires-Python: >=3.7
